MANIFEST.in
README.rst
setup.py
pinyin_jyutping_sentence/__init__.py
pinyin_jyutping_sentence/cccanto-webdist-160115.txt
pinyin_jyutping_sentence/cccedict-canto-readings-150923.txt
pinyin_jyutping_sentence/cedict_1_0_ts_utf-8_mdbg.txt
pinyin_jyutping_sentence/dict.txt.big
pinyin_jyutping_sentence/mandarin_cantonese_data.json
pinyin_jyutping_sentence.egg-info/PKG-INFO
pinyin_jyutping_sentence.egg-info/SOURCES.txt
pinyin_jyutping_sentence.egg-info/dependency_links.txt
pinyin_jyutping_sentence.egg-info/not-zip-safe
pinyin_jyutping_sentence.egg-info/requires.txt
pinyin_jyutping_sentence.egg-info/top_level.txt