Metadata-Version: 1.1
Name: pinyin-jyutping-sentence
Version: 1.3
Summary: Convert a Chinese sentence to Pinyin or Jyutping
Home-page: https://github.com/lucwastiaux/python-pinyin-jyutping-sentence
Author: Luc Wastiaux
Author-email: lucw@airpost.net
License: GPL
Platform: UNKNOWN
Classifier: Programming Language :: Python :: 3.7
Classifier: Topic :: Text Processing :: Linguistic
